backtest_equities/__init__.py
backtest_equities/backtest_equities.py
backtest_equities/run.py
backtest_equities/support_func.py
backtest_equities-0.3.5.dist-info/LICENSE
backtest_equities-0.3.5.dist-info/METADATA
backtest_equities-0.3.5.dist-info/WHEEL
backtest_equities-0.3.5.dist-info/top_level.txt
backtest_equities-0.3.5.dist-info/RECORD
