Metadata-Version: 2.1
Name: backtest_equities
Version: 0.3.5
Summary: A tool for simulating trading strategies against historical market data to evaluate performance and refine approaches before live trading.
Home-page: https://github.com/JackMartinDev/backtest_equities
Author: Jack Martin
Author-email: Jack Martin <jack.martin.codes@gmail.com>
Project-URL: Homepage, https://github.com/JackMartinDev/backtest_equities
Project-URL: Issues, https://github.com/JackMartinDev/backtest_equities/issues
Classifier: Programming Language :: Python :: 3
Classifier: License :: OSI Approved :: The Unlicense (Unlicense)
Classifier: Operating System :: OS Independent
Requires-Python: >=3.8
License-File: LICENSE
